{"user_name":"ょ","icon":1024141,"rank":725,"bestscore":2905672,"party_name":"カズマさん","strength":32001,"party":[{"form_no":1,"main":1024126,"sub1":1024141,"sub2":1014142,"weapon":410205,"acc":223145,"specialskill":102001},{"form_no":2,"main":1134100,"sub1":1134110,"sub2":1134117,"weapon":411305,"acc":224145,"specialskill":113002},{"form_no":3,"main":1153143,"sub1":1153125,"sub2":1153112,"weapon":124556,"acc":223145,"specialskill":115001},{"form_no":4,"main":1064107,"sub1":1063126,"sub2":1063116,"weapon":314406,"acc":224125,"specialskill":106002},{"form_no":5,"main":1102102,"sub1":1104100,"sub2":1023104,"weapon":314405,"acc":223145,"specialskill":110002}],"member":[{"member_id":1024126,"lv":60,"ex_flg":1},{"member_id":1024141,"lv":60,"ex_flg":1},{"member_id":1014142,"lv":60,"ex_flg":1},{"member_id":1134100,"lv":60,"ex_flg":1},{"member_id":1134110,"lv":60,"ex_flg":1},{"member_id":1134117,"lv":60,"ex_flg":1},{"member_id":1153143,"lv":60,"ex_flg":1},{"member_id":1153125,"lv":60,"ex_flg":1},{"member_id":1153112,"lv":60,"ex_flg":1},{"member_id":1064107,"lv":60,"ex_flg":1},{"member_id":1063126,"lv":60,"ex_flg":1},{"member_id":1063116,"lv":60,"ex_flg":1},{"member_id":1102102,"lv":60,"ex_flg":1},{"member_id":1104100,"lv":60,"ex_flg":1},{"member_id":1023104,"lv":60,"ex_flg":1}],"status":0,"time":1616491947,"remotedata":[],"notificationdata":[]}